evermore/__init__.py
evermore/loss.py
evermore/pdf.py
evermore/py.typed
evermore/util.py
evermore/binned/__init__.py
evermore/binned/effect.py
evermore/binned/modifier.py
evermore/binned/staterror.py
evermore/parameters/__init__.py
evermore/parameters/filter.py
evermore/parameters/parameter.py
evermore/parameters/sample.py
evermore/parameters/transform.py
evermore-0.4.1.dist-info/METADATA
evermore-0.4.1.dist-info/WHEEL
evermore-0.4.1.dist-info/licenses/LICENSE
evermore-0.4.1.dist-info/RECORD
