Metadata-Version: 2.4
Name: evermore
Version: 0.4.1
Summary: Differentiable (binned) likelihoods in JAX.
Project-URL: Homepage, https://github.com/pfackeldey/evermore
Project-URL: Bug Tracker, https://github.com/pfackeldey/evermore/issues
Project-URL: Discussions, https://github.com/pfackeldey/evermore/discussions
Project-URL: Changelog, https://github.com/pfackeldey/evermore/releases
Author-email: Peter Fackeldey <fackeldey.peter@gmail.com>
License-Expression: BSD-3-Clause
License-File: LICENSE
Classifier: Development Status :: 1 - Planning
Classifier: Intended Audience :: Developers
Classifier: Intended Audience :: Science/Research
Classifier: Operating System :: OS Independent
Classifier: Programming Language :: Python
Classifier: Programming Language :: Python :: 3
Classifier: Programming Language :: Python :: 3 :: Only
Classifier: Programming Language :: Python :: 3.11
Classifier: Programming Language :: Python :: 3.12
Classifier: Programming Language :: Python :: 3.13
Classifier: Topic :: Scientific/Engineering
Classifier: Typing :: Typed
Requires-Python: >=3.11
Requires-Dist: flax>=0.12.0
Requires-Dist: jax>=0.7.2
Requires-Dist: jaxlib
Requires-Dist: jaxtyping
